{
  "Data Analyst": {
    "technical": [
      "What is the difference between INNER JOIN and LEFT JOIN?",
      "Explain normalization in databases and its different forms.",
      "What is pandas and how do you use it for data analysis?",
      "How do you handle missing values in a dataset?",
      "What is the difference between GROUP BY and ORDER BY?",
      "Explain the concept of data cleaning and its importance.",
      "What are the different types of data visualization charts?",
      "How do you calculate mean, median, and mode in SQL?",
      "What is a pivot table and when would you use it?",
      "Explain correlation vs causation with an example.",
      "What is the difference between UNION and UNION ALL?",
      "How do you aggregate data across multiple tables?",
      "Explain window functions in SQL with examples.",
      "What is ETL and how does it relate to data analysis?",
      "How do you identify outliers in a dataset?",
      "What is the difference between HAVING and WHERE clause?",
      "Explain subqueries and when to use them.",
      "What is data wrangling and what tools do you use?",
      "How do you create calculated fields in Tableau/Power BI?",
      "What statistical tests do you commonly use in analysis?"
    ],
    "hr": [
      "Tell me about yourself.",
      "Why do you want to work as a Data Analyst?",
      "Describe a time you had to present data to non-technical stakeholders.",
      "How do you prioritize multiple analysis requests?",
      "Where do you see yourself in 5 years?",
      "Tell me about a time when your analysis led to a business decision.",
      "How do you handle conflicting data from different sources?",
      "Describe a challenging dataset you worked with.",
      "How do you ensure data accuracy in your reports?",
      "What motivates you to work with data?"
    ],
    "aptitude": [
      "If a train travels at 60 km/h, how long to cover 180 km?",
      "What is 15% of 240?",
      "If 3 workers can complete a task in 6 days, how many days will 6 workers take?",
      "A product's price increases by 20%, then decreases by 20%. What is the net change?",
      "Find the next number: 2, 6, 12, 20, 30, ?",
      "A dataset has 1000 records. If 25% are invalid, how many valid records remain?",
      "Calculate the average: 45, 67, 89, 23, 56",
      "If monthly growth is 5%, what is the yearly growth rate (compounded)?",
      "What percentage is 45 of 180?",
      "If sample A has mean 50 and sample B has mean 70, what is the combined mean for equal-sized samples?"
    ]
  },
  "Machine Learning Engineer": {
    "technical": [
      "What is the difference between supervised and unsupervised learning?",
      "Explain overfitting and how to prevent it.",
      "What is cross-validation and why is it important?",
      "Describe the bias-variance tradeoff.",
      "What are the steps in a typical ML pipeline?",
      "How do you handle imbalanced datasets?",
      "Explain gradient descent and its variants.",
      "What is regularization and what are L1 and L2 regularization?",
      "Describe precision, recall, and F1 score.",
      "What is the difference between bagging and boosting?",
      "Explain the architecture of a Neural Network.",
      "What is backpropagation and how does it work?",
      "How do you select the right algorithm for a problem?",
      "What is transfer learning and when would you use it?",
      "Explain the ROC curve and AUC.",
      "What is feature selection and what methods do you know?",
      "How do CNNs work for image classification?",
      "What is the difference between batch and stochastic gradient descent?",
      "Explain hyperparameter tuning techniques.",
      "What is model deployment and what challenges exist?"
    ],
    "hr": [
      "Tell me about yourself.",
      "Why do you want to be a Machine Learning Engineer?",
      "Describe a challenging ML project you worked on.",
      "How do you stay updated with the latest ML research?",
      "How do you explain ML concepts to non-technical team members?",
      "Tell me about a model that didn't perform as expected. What did you do?",
      "How do you handle ethical concerns in AI/ML?",
      "Describe your experience working with cross-functional teams.",
      "What's the most interesting ML paper you've read recently?",
      "How do you balance model complexity with interpretability?"
    ],
    "aptitude": [
      "A model has 85% accuracy. If it makes 1000 predictions, how many are likely wrong?",
      "If training time doubles with each additional feature, how long for 10 features if 1 feature takes 2 minutes?",
      "Calculate the probability of getting at least one 6 in two dice rolls.",
      "What is the expected value when rolling a fair die?",
      "Find the pattern: 1, 1, 2, 3, 5, 8, ?",
      "If precision is 0.9 and recall is 0.8, calculate F1 score.",
      "A model has 95% specificity and 90% sensitivity. Calculate the false positive rate.",
      "If training data is 80% of 10,000 samples, how many samples for validation?",
      "Calculate the Euclidean distance between points (3,4) and (6,8).",
      "If batch size is 32 and dataset has 10,000 samples, how many batches per epoch?"
    ]
  },
  "Frontend Developer": {
    "technical": [
      "What is the difference between let, const, and var in JavaScript?",
      "Explain the CSS box model.",
      "What is the virtual DOM in React?",
      "How do you optimize website performance?",
      "What is the difference between == and === in JavaScript?",
      "Explain React hooks and their benefits.",
      "What is responsive design and how do you implement it?",
      "What are closures in JavaScript?",
      "Explain the difference between CSS Grid and Flexbox.",
      "What is the purpose of useEffect in React?",
      "What is event bubbling and event capturing?",
      "Explain the concept of state management in frontend apps.",
      "What is lazy loading and how do you implement it?",
      "How does the browser rendering engine work?",
      "What is the difference between cookies, localStorage, and sessionStorage?",
      "Explain the concept of Progressive Web Apps (PWA).",
      "What are Web Workers and when would you use them?",
      "How do you handle cross-browser compatibility?",
      "What is the purpose of React.memo and useMemo?",
      "Explain CSS specificity and how it works."
    ],
    "hr": [
      "Tell me about yourself.",
      "Why do you want to be a Frontend Developer?",
      "Describe a project where you improved user experience.",
      "How do you handle feedback on your design implementations?",
      "How do you stay current with frontend technologies?",
      "Tell me about a time you had to optimize a slow website.",
      "How do you collaborate with designers and backend developers?",
      "Describe your experience with accessibility (a11y).",
      "What's your approach to learning new frontend frameworks?",
      "How do you handle browser-specific bugs?"
    ],
    "aptitude": [
      "If a webpage takes 3 seconds to load and you optimize it by 40%, what is the new load time?",
      "A website has 1000 visitors daily. If conversion rate is 2.5%, how many conversions per week?",
      "Calculate the aspect ratio of a 1920x1080 image.",
      "If CSS file is 50KB and needs to be reduced by 30%, what is the target size?",
      "Find the output: console.log(typeof [])",
      "If render time is 16ms for 60fps, how many frames per second at 32ms?",
      "A bundle is 500KB. After code splitting into 5 equal chunks, what is each chunk size?",
      "If 80% of users are on mobile and 20% on desktop, how many mobile users out of 5000?",
      "Calculate the viewport width if 1rem = 16px and element width is 20rem.",
      "If image is compressed from 2MB to 200KB, what is the compression ratio?"
    ]
  },
  "Backend Developer": {
    "technical": [
      "Explain RESTful API design principles.",
      "What is the difference between SQL and NoSQL databases?",
      "How do you handle authentication and authorization?",
      "What is middleware in web frameworks?",
      "Explain database indexing and its importance.",
      "What is the difference between PUT and PATCH?",
      "How do you design for scalability?",
      "What is caching and when would you use it?",
      "Explain the concept of microservices.",
      "What is rate limiting and why is it important?",
      "Explain ACID properties in databases.",
      "What is database sharding and when would you use it?",
      "How do you handle database migrations?",
      "What is connection pooling?",
      "Explain the difference between synchronous and asynchronous programming.",
      "What is message queue and when would you use it?",
      "How do you design an API for pagination?",
      "What is GraphQL and how does it differ from REST?",
      "Explain the N+1 query problem and how to solve it.",
      "What are best practices for API security?"
    ],
    "hr": [
      "Tell me about yourself.",
      "Why do you want to be a Backend Developer?",
      "Describe a time you debugged a complex issue.",
      "How do you ensure code quality in your projects?",
      "How do you handle tight deadlines?",
      "Tell me about a time you had to optimize a slow query.",
      "How do you approach system design problems?",
      "Describe your experience with code reviews.",
      "How do you handle production incidents?",
      "What's your approach to writing testable code?"
    ],
    "aptitude": [
      "An API handles 100 requests per second. How many requests in 15 minutes?",
      "If database query takes 200ms and you need to run 50 queries, what is total time in sequential execution?",
      "A server has 8GB RAM and each process uses 512MB. How many processes can run?",
      "Calculate the response time if network latency is 50ms and processing time is 150ms.",
      "If 3 servers can handle 3000 requests, how many servers for 9000 requests?",
      "What is the time complexity of binary search?",
      "If cache hit rate is 80% and database query takes 100ms, cache takes 5ms, what is average response time?",
      "Calculate throughput if 1000 requests are processed in 10 seconds.",
      "If replication factor is 3 and data size is 1TB, what is total storage needed?",
      "A queue processes 50 messages per minute. How long to process 500 messages?"
    ]
  },
  "Full Stack Developer": {
    "technical": [
      "What technologies make up the MERN stack?",
      "How do you manage state in a full-stack application?",
      "Explain the request-response cycle in web applications.",
      "What is CORS and how do you handle it?",
      "How do you structure a full-stack project?",
      "What is JWT and how is it used for authentication?",
      "Explain the concept of API versioning.",
      "What is server-side rendering vs client-side rendering?",
      "How do you handle file uploads in a web application?",
      "What is WebSocket and when would you use it?",
      "How do you implement real-time features in web apps?",
      "Explain the concept of ORM and its benefits.",
      "What is database connection management in node.js?",
      "How do you handle environment variables in different stages?",
      "What is the role of a reverse proxy?",
      "How do you implement search functionality in a full-stack app?",
      "What is the difference between monolith and microservices?",
      "How do you handle form validation on both frontend and backend?",
      "Explain session management vs token-based auth.",
      "What tools do you use for API documentation?"
    ],
    "hr": [
      "Tell me about yourself.",
      "Why do you want to be a Full Stack Developer?",
      "Describe a full-stack project you built from scratch.",
      "How do you decide between frontend and backend focus?",
      "How do you manage learning multiple technologies?",
      "Tell me about a time you had to integrate frontend with backend.",
      "How do you handle disagreements with team members?",
      "What's your approach to debugging full-stack issues?",
      "How do you prioritize features in a project?",
      "Describe your experience with agile development."
    ],
    "aptitude": [
      "A full-stack app has 3 frontend pages and 5 API endpoints. How many integration points?",
      "If frontend build takes 2 minutes and backend build takes 3 minutes, what is parallel build time?",
      "Calculate storage needed for 1000 users with 5MB data each.",
      "A deployment pipeline has 4 stages of 5 minutes each. What is the total deployment time?",
      "If bug rate is 2 per 100 lines, how many bugs in a 5000 line codebase?",
      "If frontend is 40% of work and backend is 60%, how many hours for backend in a 100-hour project?",
      "Calculate the number of API calls if each page makes 3 calls and user visits 10 pages.",
      "If database is 2GB and grows 10% monthly, what size after 6 months?",
      "A feature needs 5 frontend components and 3 API endpoints. If each takes 2 hours, total time?",
      "If test coverage is 80% and there are 500 functions, how many are untested?"
    ]
  },
  "Data Scientist": {
    "technical": [
      "What is the difference between Data Science and Machine Learning?",
      "Explain the Central Limit Theorem.",
      "What is feature engineering and why is it important?",
      "How do you validate a predictive model?",
      "What is A/B testing and how do you design one?",
      "Explain the difference between Type I and Type II errors.",
      "What is dimensionality reduction and when do you use it?",
      "How do you communicate findings to stakeholders?",
      "What is the purpose of exploratory data analysis?",
      "Explain hypothesis testing with an example.",
      "What is the difference between parametric and non-parametric tests?",
      "Explain p-value and confidence intervals.",
      "What is PCA and how does it work?",
      "How do you handle multicollinearity?",
      "What is the difference between classification and regression?",
      "Explain the concept of ensemble methods.",
      "What is time series analysis and its components?",
      "How do you detect and handle seasonality in data?",
      "What is the curse of dimensionality?",
      "Explain the difference between descriptive and inferential statistics."
    ],
    "hr": [
      "Tell me about yourself.",
      "Why do you want to be a Data Scientist?",
      "Describe a project where data drove a business decision.",
      "How do you handle ambiguous problem statements?",
      "How do you balance statistical rigor with business timelines?",
      "Tell me about a time your analysis was challenged.",
      "How do you explain complex statistical concepts to non-technical stakeholders?",
      "Describe your experience with cross-functional collaboration.",
      "What's the most impactful insight you've discovered?",
      "How do you stay updated with data science trends?"
    ],
    "aptitude": [
      "If a sample mean is 50 with standard deviation 10, what is the z-score for value 70?",
      "Calculate the probability of drawing 2 red balls in a row from a bag with 3 red and 7 blue balls.",
      "What is the 95th percentile in a standard normal distribution?",
      "If correlation coefficient is 0.8, what percentage of variance is explained?",
      "A dataset has 1000 records. After removing 15% outliers, how many records remain?",
      "Calculate the sample size needed for 95% confidence level with 5% margin of error.",
      "If mean is 100 and median is 80, is the distribution left or right skewed?",
      "Calculate the coefficient of variation if mean is 50 and std dev is 10.",
      "What is the probability of getting exactly 3 heads in 5 coin flips?",
      "If R-squared is 0.64, what is the correlation coefficient?"
    ]
  },
  "DevOps Engineer": {
    "technical": [
      "What is CI/CD and why is it important?",
      "Explain the difference between Docker and Kubernetes.",
      "What is Infrastructure as Code?",
      "How do you monitor application health?",
      "What is a blue-green deployment?",
      "Explain the concept of containerization.",
      "What tools do you use for configuration management?",
      "How do you handle secrets management?",
      "What is a service mesh?",
      "Explain the 12-factor app methodology.",
      "What is GitOps and how does it work?",
      "How do you implement zero-downtime deployments?",
      "What is the difference between horizontal and vertical scaling?",
      "Explain the concept of immutable infrastructure.",
      "What is observability and its three pillars?",
      "How do you implement disaster recovery?",
      "What is the difference between containers and VMs?",
      "Explain pod networking in Kubernetes.",
      "What is a Helm chart?",
      "How do you handle log aggregation?"
    ],
    "hr": [
      "Tell me about yourself.",
      "Why do you want to be a DevOps Engineer?",
      "Describe a time you improved deployment processes.",
      "How do you handle production incidents?",
      "How do you balance speed vs stability in deployments?",
      "Tell me about a time you automated a manual process.",
      "How do you collaborate with development teams?",
      "Describe your experience with on-call responsibilities.",
      "What's your approach to documenting infrastructure?",
      "How do you handle technical debt in infrastructure?"
    ],
    "aptitude": [
      "If deployment frequency is 10 times per day, how many deployments per month (30 days)?",
      "A container uses 256MB RAM. How many containers can fit in 4GB?",
      "If mean time to recovery is 30 minutes and there are 4 incidents per month, what is total downtime?",
      "Calculate uptime percentage if service was down for 4 hours in a month.",
      "If a pipeline stage fails 5% of the time, what is the probability of 3 consecutive successes?",
      "If each node handles 1000 requests and load is 5000, how many nodes needed with 50% buffer?",
      "Calculate the number of replicas if each handles 100 users and expected users are 500 with 2x scaling factor.",
      "If backup takes 2 hours and runs daily, what is the monthly backup time?",
      "A cluster has 5 nodes. If one fails, what percentage of capacity remains?",
      "If log retention is 30 days and daily logs are 10GB, what storage is needed?"
    ]
  },
  "Software Engineer": {
    "technical": [
      "What are SOLID principles?",
      "Explain the difference between stack and heap memory.",
      "What is the difference between process and thread?",
      "Explain object-oriented programming concepts.",
      "What is Big O notation and why is it important?",
      "Describe common design patterns you've used.",
      "What is the difference between interface and abstract class?",
      "Explain the concept of dependency injection.",
      "What is a deadlock and how do you prevent it?",
      "How do you write unit tests effectively?",
      "What is polymorphism and give an example.",
      "Explain the concept of clean code.",
      "What is the purpose of code reviews?",
      "How do you handle exception handling?",
      "What is the difference between composition and inheritance?",
      "Explain the concept of immutability.",
      "What is recursion and when should you use it?",
      "How do you approach debugging a complex issue?",
      "What is technical debt and how do you manage it?",
      "Explain the CAP theorem."
    ],
    "hr": [
      "Tell me about yourself.",
      "Why do you want to be a Software Engineer?",
      "Describe a challenging technical problem you solved.",
      "How do you handle code reviews and feedback?",
      "How do you stay updated with technology trends?",
      "Tell me about a project you're most proud of.",
      "How do you handle disagreements with teammates?",
      "Describe your experience working in an agile environment.",
      "What's your approach to learning new technologies?",
      "How do you balance between quick fixes and proper solutions?"
    ],
    "aptitude": [
      "What is the time complexity of sorting algorithms?",
      "If a function is called recursively 5 times, how many stack frames are created?",
      "Calculate the space complexity of storing n elements in an array.",
      "If a loop runs n times and inner loop runs m times, what is total iterations?",
      "A binary tree has 7 nodes. What is the maximum height?",
      "If memory is 4GB and each object is 1KB, maximum objects that can be created?",
      "Calculate the number of comparisons in binary search for 1000 elements.",
      "If code has 3 nested loops of n, what is time complexity?",
      "A hash table has 100 buckets and 50 elements. What is the load factor?",
      "If function A calls B, B calls C, what is the call stack depth?"
    ]
  },
  "Cloud Engineer": {
    "technical": [
      "What is the difference between IaaS, PaaS, and SaaS?",
      "Explain VPC and its components.",
      "What is auto-scaling and how does it work?",
      "How do you secure cloud resources?",
      "What is the difference between public and private subnets?",
      "Explain the concept of load balancing.",
      "What is serverless computing?",
      "How do you optimize cloud costs?",
      "What is a CDN and when would you use it?",
      "Explain IAM roles and policies.",
      "What is the difference between S3 storage classes?",
      "How do you implement high availability?",
      "What is cloud migration and its strategies?",
      "Explain the concept of edge computing.",
      "What is a NAT gateway?",
      "How do you handle data backup in cloud?",
      "What is the shared responsibility model?",
      "Explain multi-region deployments.",
      "What is cloud-native architecture?",
      "How do you monitor cloud resources?"
    ],
    "hr": [
      "Tell me about yourself.",
      "Why do you want to be a Cloud Engineer?",
      "Describe a cloud migration project you worked on.",
      "How do you handle security in cloud environments?",
      "How do you stay updated with cloud services?",
      "Tell me about a time you optimized cloud costs.",
      "How do you handle vendor lock-in concerns?",
      "Describe your experience with multi-cloud environments.",
      "What's your approach to cloud architecture design?",
      "How do you balance cost vs performance in cloud?"
    ],
    "aptitude": [
      "If EC2 instance costs $0.10/hour, what is monthly cost (720 hours)?",
      "A Lambda function runs 1 million times at $0.20 per million. What is the cost?",
      "If S3 storage is $0.023 per GB and you store 100GB, what is monthly cost?",
      "Calculate data transfer cost if rate is $0.09/GB and transfer is 500GB.",
      "If auto-scaling adds 2 instances every 1000 requests, how many instances for 5000?",
      "A region has 3 availability zones. If each has 2 subnets, total subnets?",
      "If reserved instance saves 30% and on-demand is $100/month, what is reserved cost?",
      "Calculate the number of S3 PUT requests if file count is 10,000.",
      "If CloudFront handles 80% of traffic, what reaches origin for 1 million requests?",
      "A VPC has CIDR /16. How many IP addresses are available?"
    ]
  },
  "Product Manager": {
    "technical": [
      "How do you prioritize features in a product roadmap?",
      "What is the difference between MVP and MLP?",
      "How do you measure product success?",
      "What is user story mapping?",
      "Explain the concept of product-market fit.",
      "What metrics do you track for a product?",
      "How do you conduct user research?",
      "What is A/B testing in product context?",
      "How do you handle technical debt discussions?",
      "What is the role of data in product decisions?",
      "Explain the concept of OKRs.",
      "How do you create a product roadmap?",
      "What is competitive analysis?",
      "How do you define success criteria for a feature?",
      "What is the difference between output and outcome?"
    ],
    "hr": [
      "Tell me about yourself.",
      "Why do you want to be a Product Manager?",
      "Describe a product you launched from scratch.",
      "How do you handle conflicting stakeholder requirements?",
      "Tell me about a product decision that failed.",
      "How do you collaborate with engineering teams?",
      "Describe your approach to gathering user feedback.",
      "How do you say no to feature requests?",
      "What's the most successful product you've worked on?",
      "How do you balance user needs vs business goals?"
    ],
    "aptitude": [
      "If conversion rate is 2% and you have 10,000 visitors, how many conversions?",
      "Calculate retention rate if 1000 users signed up and 700 are active after 30 days.",
      "If NPS is calculated as % promoters - % detractors, what is NPS if 60% promoters and 20% detractors?",
      "A feature is used by 40% of users. If you have 5000 users, how many use the feature?",
      "Calculate MRR if you have 100 customers paying $50/month.",
      "If churn rate is 5% monthly, how many customers remain from 1000 after 1 month?",
      "What is the LTV if average subscription is $100/month and average lifetime is 24 months?",
      "If CAC is $500 and LTV is $2000, what is the LTV:CAC ratio?",
      "Calculate daily active users if weekly is 70,000 and ratio is 1:7.",
      "If feature adoption is 30% in week 1 and grows 10% weekly, what is week 3 adoption?"
    ]
  }
}
